Metadata-Version: 2.1
Name: pymnet
Version: 1.0.0
Summary: Multilayer network analysis library for Python
Author-email: Mikko Kivelä <mikko.kivela@iki.fi>
License: GPLv3
Project-URL: homepage, https://mnets.github.io/pymnet/
Project-URL: documentation, https://mnets.github.io/pymnet/
Project-URL: repository, https://github.com/mnets/pymnet
Project-URL: bug-tracker, https://github.com/mnets/pymnet/issues
Keywords: Complex Networks,Networks,network,Graphs,Graph Theory,graph,Multilayer Networks,multilayer network
Classifier: Development Status :: 4 - Beta
Classifier: Intended Audience :: Education
Classifier: Intended Audience :: Science/Research
Classifier: License :: OSI Approved :: MIT License
Classifier: Operating System :: POSIX :: Linux
Classifier: Programming Language :: C++
Classifier: Programming Language :: Python :: 3
Classifier: Programming Language :: Python :: Implementation :: CPython
Classifier: Topic :: Scientific/Engineering
Classifier: Topic :: Scientific/Engineering :: Physics
Classifier: Topic :: Scientific/Engineering :: Mathematics
Classifier: Topic :: Scientific/Engineering :: Information Analysis
Requires-Python: >=3.8
License-File: LICENSE.txt
Requires-Dist: matplotlib >=3.7.0
Requires-Dist: numpy >=1.23.0
Requires-Dist: scipy >=1.10.0
Requires-Dist: networkx <4.0,>=2.0
Requires-Dist: bliss-bind >=0.3.0 ; (sys_platform == "darwin" or ((platform_machine == "x86_64" and sys_platform == "linux") or (platform_machine == "AMD64" and sys_platform == "win32"))) and python_version >= "3.8"
Provides-Extra: dev
Requires-Dist: black >=24.4 ; extra == 'dev'
Requires-Dist: isort >=5.13 ; extra == 'dev'
Provides-Extra: test
Requires-Dist: coverage >=7.0 ; extra == 'test'
Provides-Extra: tutorial
Requires-Dist: jupyterlab >=4.2 ; extra == 'tutorial'
Requires-Dist: pandas ; extra == 'tutorial'
